{"mockup":{"controls":{"control":[{"ID":"0","measuredH":"977.5","measuredW":"925","properties":{"direction":"horizontal","text":"Source Data\n- Skip Already Processed\n- Check Item Template\n- Ensure Item\n-- Resolve Parent\n-- Resolve Template\n-- Ensure Folders\n-- Create Item\n- Migrate Latest Approved Version per Language\n-- Skip Unversioned Media\n-- Ensure Language Version\n-- Begin Edit\n-- Migrate Fields\n--- Skip Fields\n--- Skip Media Fields\n--- Skip Standard Fields\n--- Resolve Field\n--- Copy Value\n--- Process Media\n-- Finalize Workflow\n-- End Edit\n-- Attach Versioned Media\n- Attached Unversioned Media"},"typeID":"SiteMap","x":"192","y":"138","zOrder":"0"},{"ID":"1","h":"108","measuredH":"123","measuredW":"109","properties":{"text":"Data from source via \nSitecore Rocks - \nHard Rock Web Service"},"typeID":"StickyNote","w":"172","x":"133","y":"407","zOrder":"1"},{"ID":"2","h":"79","measuredH":"123","measuredW":"109","properties":{"text":"Pipeline called per Item"},"typeID":"StickyNote","w":"150","x":"254","y":"19","zOrder":"2"},{"ID":"3","h":"86","measuredH":"123","measuredW":"109","properties":{"text":"Pipeline called per Version"},"typeID":"StickyNote","w":"135","x":"502","y":"435","zOrder":"3"},{"ID":"4","h":"89","measuredH":"123","measuredW":"109","properties":{"text":"Pipeline called per Field"},"typeID":"StickyNote","w":"113","x":"944","y":"448","zOrder":"4"},{"ID":"5","h":"65","measuredH":"64","measuredW":"10","properties":{"color":"13369344","curvature":"0","direction":"top","leftArrow":"false","p0":{"y":0,"x":0,"length":0},"p1":{"y":0,"x":0.5,"length":0.5},"p2":{"y":64,"x":10,"length":64.77653896280658},"shape":"bezier"},"typeID":"Arrow","w":"11","x":"222","y":"515","zOrder":"5"},{"ID":"6","h":"52","measuredH":"51","measuredW":"2","properties":{"color":"13369344","curvature":"0","direction":"top","leftArrow":"false","p0":{"y":0,"x":0,"length":0},"p1":{"y":0,"x":0.5,"length":0.5},"p2":{"y":51,"x":2,"length":51.03920062069938},"shape":"bezier"},"typeID":"Arrow","w":"3","x":"330","y":"98","zOrder":"6"},{"ID":"7","h":"6","measuredH":"5","measuredW":"55","properties":{"color":"13369344","curvature":"0","direction":"bottom","leftArrow":"false","p0":{"y":5,"x":0,"length":5},"p1":{"y":0,"x":0.5,"length":0.5},"p2":{"y":0,"x":55,"length":55},"shape":"bezier"},"typeID":"Arrow","w":"56","x":"637","y":"480","zOrder":"7"},{"ID":"8","h":"75","measuredH":"74","measuredW":"44","properties":{"color":"13369344","curvature":"0","direction":"bottom","leftArrow":"false","p0":{"y":0,"x":44,"length":44},"p1":{"y":0,"x":0.5,"length":0.5},"p2":{"y":74,"x":0,"length":74},"shape":"bezier"},"typeID":"Arrow","w":"45","x":"921","y":"540","zOrder":"8"},{"ID":"9","measuredH":"45","measuredW":"499","properties":{"text":"Sitecore Field Migrator Flow"},"typeID":"Title","x":"494","y":"22","zOrder":"9"},{"ID":"10","h":"149","measuredH":"148","measuredW":"0","properties":{"color":"2848996","curvature":"0","direction":"top","leftArrow":"false","p0":{"y":0,"x":0,"length":0},"p1":{"y":0,"x":0.5,"length":0.5},"p2":{"y":148,"x":0,"length":148},"shape":"bezier","text":""},"typeID":"Arrow","w":"1","x":"321","y":"157","zOrder":"10"},{"ID":"11","h":"149","measuredH":"148","measuredW":"0","properties":{"color":"2848996","curvature":"0","direction":"top","leftArrow":"false","p0":{"y":0,"x":0,"length":0},"p1":{"y":0,"x":0.5,"length":0.5},"p2":{"y":148,"x":0,"length":148},"shape":"bezier","text":""},"typeID":"Arrow","w":"1","x":"593","y":"258","zOrder":"11"},{"ID":"12","h":"149","measuredH":"148","measuredW":"0","properties":{"color":"2848996","curvature":"0","direction":"top","leftArrow":"false","p0":{"y":0,"x":0,"length":0},"p1":{"y":0,"x":0.5,"length":0.5},"p2":{"y":148,"x":0,"length":148},"shape":"bezier","text":""},"typeID":"Arrow","w":"1","x":"702","y":"473","zOrder":"12"},{"ID":"13","h":"149","measuredH":"148","measuredW":"0","properties":{"color":"2848996","curvature":"0","direction":"top","leftArrow":"false","p0":{"y":0,"x":0,"length":0},"p1":{"y":0,"x":0.5,"length":0.5},"p2":{"y":148,"x":0,"length":148},"shape":"bezier","text":""},"typeID":"Arrow","w":"1","x":"898","y":"629","zOrder":"13"}]},"measuredH":"1115","measuredW":"1117","mockupH":"1096","mockupW":"984","version":"1.0"}}